{
  "status_code": 401,
  "headers": {
    "content-type": "application/json; charset=utf-8",
    "transfer-encoding": "chunked",
    "connection": "keep-alive",
    "date": "Wed, 24 Jun 2026 11:14:59 GMT",
    "expires": "-1",
    "strict-transport-security": "max-age=31536000; includeSubDomains; preload",
    "server": "WHS",
    "cache-control": "no-store, no-cache, must-revalidate, post-check=0, pre-check=0, max-age=0, s-maxage=0",
    "pragma": "no-cache",
    "x-cache": "Error from cloudfront",
    "via": "1.1 1232ef1832a7212470cbe45556a02b9a.cloudfront.net (CloudFront)",
    "x-amz-cf-pop": "WAW51-P3",
    "x-amz-cf-id": "0aLK340WP1lT6lqGlGill0WI76tzURdd0seT4iECgRRIKoeiVgelxQ==",
    "x-xss-protection": "1; mode=block",
    "x-frame-options": "SAMEORIGIN",
    "referrer-policy": "same-origin",
    "content-security-policy": "default-src 'self';script-src 'self' cdn.jsdelivr.net 'unsafe-inline';style-src 'self' 'unsafe-inline' fonts.googleapis.com;font-src 'self' fonts.gstatic.com;worker-src blob:;connect-src 'self';img-src 'self' *.cloudfront.net;media-src 'self'",
    "x-content-type-options": "nosniff"
  },
  "body": "[{\"code\":401,\"message\":\"oauth_problem=token_rejected\"}]"
}